overlab/__init__.py
overlab/overlab.py
overlab-0.2.5.dist-info/LICENSE.txt
overlab-0.2.5.dist-info/METADATA
overlab-0.2.5.dist-info/WHEEL
overlab-0.2.5.dist-info/top_level.txt
overlab-0.2.5.dist-info/RECORD
