Metadata-Version: 2.1
Name: overlab
Version: 0.2.5
Author: Francesco Gualdi
License: GPL
License-File: LICENSE.txt
